scclient/__init__.py
scclient/socket_client.py
tests/__init__.py
tests/test_socket_client.py
scclient-0.0.3.dist-info/LICENSE
scclient-0.0.3.dist-info/METADATA
scclient-0.0.3.dist-info/WHEEL
scclient-0.0.3.dist-info/top_level.txt
scclient-0.0.3.dist-info/RECORD
