Metadata-Version: 2.1
Name: scclient
Version: 0.0.3
Summary: A SocketCluster compatible WebSocket library
Home-page: https://github.com/jnesselr/scclient
Author: Justin Nesselrotte
Author-email: admin@jnesselr.org
License: MIT
Keywords: socket cluster websocket socketcluster
Platform: UNKNOWN
Classifier: License :: OSI Approved :: BSD License
Requires-Dist: websocket-client (<1.0)
Requires-Dist: pytest (>=4.4.0)
Requires-Dist: pytest-cov
Requires-Dist: codacy-coverage
